{
	"info": {
		"_postman_id": "eaf7fd33-160a-4db5-aedf-49365311a4cf",
		"name": "Service Booking System",
		"schema": "https://schema.getpostman.com/json/collection/v2.1.0/collection.json",
		"_exporter_id": "38044731"
	},
	"item": [
		{
			"name": "Public",
			"item": [
				{
					"name": "registration",
					"request": {
						"method": "POST",
						"header": [],
						"body": {
							"mode": "formdata",
							"formdata": [
								{
									"key": "name",
									"value": "John Doe",
									"type": "text"
								},
								{
									"key": "email",
									"value": "johndoe@gmail.com",
									"type": "text"
								},
								{
									"key": "password",
									"value": "12345678",
									"type": "text"
								}
							]
						},
						"url": {
							"raw": "{{base_url}}api/register",
							"host": [
								"{{base_url}}api"
							],
							"path": [
								"register"
							]
						}
					},
					"response": []
				},
				{
					"name": "login",
					"request": {
						"method": "POST",
						"header": [],
						"body": {
							"mode": "formdata",
							"formdata": [
								{
									"key": "email",
									"value": "admin@gmail.com",
									"type": "text"
								},
								{
									"key": "password",
									"value": "12345",
									"type": "text"
								}
							]
						},
						"url": {
							"raw": "{{base_url}}api/login",
							"host": [
								"{{base_url}}api"
							],
							"path": [
								"login"
							]
						}
					},
					"response": []
				},
				{
					"name": "logout",
					"request": {
						"auth": {
							"type": "bearer",
							"bearer": [
								{
									"key": "token",
									"value": "447756admin@gmail.com",
									"type": "string"
								}
							]
						},
						"method": "POST",
						"header": [
							{
								"key": "Accept",
								"value": "application/json",
								"type": "text"
							}
						],
						"url": {
							"raw": "{{base_url}}api/logout",
							"host": [
								"{{base_url}}api"
							],
							"path": [
								"logout"
							]
						}
					},
					"response": []
				}
			]
		},
		{
			"name": "Authenticated Admin",
			"item": [
				{
					"name": "Bookings",
					"request": {
						"auth": {
							"type": "bearer",
							"bearer": [
								{
									"key": "token",
									"value": "1|gY6t4wrjWGam0FSSJ9CJOTBzLyhZWZNrrv9FeWpgf5984570",
									"type": "string"
								}
							]
						},
						"method": "GET",
						"header": [
							{
								"key": "Accept",
								"value": "application/json",
								"type": "text"
							}
						],
						"url": {
							"raw": "{{base_url}}api/admin/bookings",
							"host": [
								"{{base_url}}api"
							],
							"path": [
								"admin",
								"bookings"
							]
						}
					},
					"response": []
				},
				{
					"name": "services",
					"request": {
						"auth": {
							"type": "bearer",
							"bearer": [
								{
									"key": "token",
									"value": "2|D6Kk1YDFZniisAf2x0oiOQynDl3USVePsFP54sSk2c2a127b",
									"type": "string"
								}
							]
						},
						"method": "POST",
						"header": [
							{
								"key": "Accept",
								"value": "application/json",
								"type": "text"
							}
						],
						"body": {
							"mode": "formdata",
							"formdata": [
								{
									"key": "name",
									"value": "xyz service",
									"type": "text"
								},
								{
									"key": "description",
									"value": "xyz service",
									"type": "text"
								},
								{
									"key": "price",
									"value": "12.00",
									"type": "text"
								}
							]
						},
						"url": {
							"raw": "{{base_url}}api/services",
							"host": [
								"{{base_url}}api"
							],
							"path": [
								"services"
							]
						}
					},
					"response": []
				},
				{
					"name": "Update Services",
					"request": {
						"auth": {
							"type": "bearer",
							"bearer": [
								{
									"key": "token",
									"value": "3|4UT2NblNTceXNVtHeP22wNjscTseQ22sfBM2fFVNf45acf1e",
									"type": "string"
								}
							]
						},
						"method": "PUT",
						"header": [
							{
								"key": "Accept",
								"value": "application/json",
								"type": "text"
							},
							{
								"key": "Content-Type",
								"value": "application/json",
								"type": "text"
							}
						],
						"body": {
							"mode": "raw",
							"raw": "{\r\n    \"name\": \"Home Decorating Here\",\r\n    \"description\": \"Professional home decorating services\",\r\n    \"price\": 12.00\r\n}"
						},
						"url": {
							"raw": "{{base_url}}api/services/1",
							"host": [
								"{{base_url}}api"
							],
							"path": [
								"services",
								"1"
							]
						}
					},
					"response": []
				},
				{
					"name": "Delete Service",
					"request": {
						"auth": {
							"type": "bearer",
							"bearer": [
								{
									"key": "token",
									"value": "3|4UT2NblNTceXNVtHeP22wNjscTseQ22sfBM2fFVNf45acf1e",
									"type": "string"
								}
							]
						},
						"method": "DELETE",
						"header": [
							{
								"key": "Accept",
								"value": "application/json",
								"type": "text"
							},
							{
								"key": "Content-Type",
								"value": "application/json",
								"type": "text"
							}
						],
						"body": {
							"mode": "raw",
							"raw": "{\r\n    \"name\": \"Home Decorating Here\",\r\n    \"description\": \"Professional home decorating services\",\r\n    \"price\": 12.00\r\n}"
						},
						"url": {
							"raw": "{{base_url}}api/services/4",
							"host": [
								"{{base_url}}api"
							],
							"path": [
								"services",
								"4"
							]
						}
					},
					"response": []
				}
			]
		},
		{
			"name": "Authenticated Customer",
			"item": [
				{
					"name": "Get Services",
					"request": {
						"auth": {
							"type": "bearer",
							"bearer": [
								{
									"key": "token",
									"value": "3|4UT2NblNTceXNVtHeP22wNjscTseQ22sfBM2fFVNf45acf1e",
									"type": "string"
								}
							]
						},
						"method": "GET",
						"header": [
							{
								"key": "Accept",
								"value": "application/json",
								"type": "text"
							}
						],
						"url": {
							"raw": "{{base_url}}api/services",
							"host": [
								"{{base_url}}api"
							],
							"path": [
								"services"
							]
						}
					},
					"response": []
				},
				{
					"name": "New Request",
					"request": {
						"auth": {
							"type": "bearer",
							"bearer": [
								{
									"key": "token",
									"value": "1|gY6t4wrjWGam0FSSJ9CJOTBzLyhZWZNrrv9FeWpgf5984570",
									"type": "string"
								}
							]
						},
						"method": "POST",
						"header": [
							{
								"key": "Accept",
								"value": "application/json",
								"type": "text"
							}
						],
						"body": {
							"mode": "formdata",
							"formdata": [
								{
									"key": "user_id",
									"value": "3",
									"type": "text"
								},
								{
									"key": "service_id",
									"value": "1",
									"type": "text"
								},
								{
									"key": "booking_date",
									"value": "2025-07-30",
									"type": "text"
								}
							]
						},
						"url": {
							"raw": "{{base_url}}api/bookings",
							"host": [
								"{{base_url}}api"
							],
							"path": [
								"bookings"
							]
						}
					},
					"response": []
				}
			]
		}
	],
	"event": [
		{
			"listen": "prerequest",
			"script": {
				"type": "text/javascript",
				"packages": {},
				"exec": [
					""
				]
			}
		},
		{
			"listen": "test",
			"script": {
				"type": "text/javascript",
				"packages": {},
				"exec": [
					""
				]
			}
		}
	],
	"variable": [
		{
			"key": "base_url",
			"value": "http://service-booking-system.test/",
			"type": "string"
		}
	]
}